test/__init__.py
test/test.py
tp136-0.1.0.dist-info/METADATA
tp136-0.1.0.dist-info/WHEEL
tp136-0.1.0.dist-info/top_level.txt
tp136-0.1.0.dist-info/RECORD
